MANIFEST.in
README.rst
setup.py
rattail_tutorial/__init__.py
rattail_tutorial/_version.py
rattail_tutorial/commands.py
rattail_tutorial/config.py
rattail_tutorial/emails.py
rattail_tutorial.egg-info/PKG-INFO
rattail_tutorial.egg-info/SOURCES.txt
rattail_tutorial.egg-info/dependency_links.txt
rattail_tutorial.egg-info/entry_points.txt
rattail_tutorial.egg-info/requires.txt
rattail_tutorial.egg-info/top_level.txt
rattail_tutorial/db/__init__.py
rattail_tutorial/db/model/__init__.py
rattail_tutorial/db/model/core.py
rattail_tutorial/web/__init__.py
rattail_tutorial/web/app.py
rattail_tutorial/web/menus.py
rattail_tutorial/web/subscribers.py
rattail_tutorial/web/static/__init__.py
rattail_tutorial/web/templates/base_meta.mako
rattail_tutorial/web/templates/home.mako
rattail_tutorial/web/templates/login.mako
rattail_tutorial/web/templates/mobile/base.mako
rattail_tutorial/web/templates/mobile/home.mako
rattail_tutorial/web/views/__init__.py
rattail_tutorial/web/views/common.py