Metadata-Version: 1.1
Name: rattail-tutorial
Version: 0.1.0
Summary: Rattail Development Tutorial
Home-page: https://rattailproject.org
Author: Lance Edgar
Author-email: lance@edbob.org
License: GNU GPL v3
Platform: UNKNOWN
Classifier: Development Status :: 3 - Alpha
Classifier: Environment :: Console
Classifier: Environment :: Web Environment
Classifier: Framework :: Pyramid
Classifier: Intended Audience :: Developers
Classifier: Natural Language :: English
Classifier: Operating System :: POSIX :: Linux
Classifier: Programming Language :: Python
Classifier: Programming Language :: Python :: 3
Classifier: Topic :: Office/Business
